fabricatio_agent-0.2.4.dist-info/METADATA
fabricatio_agent-0.2.4.dist-info/WHEEL
fabricatio_agent-0.2.4.dist-info/entry_points.txt
fabricatio_agent/__init__.py
fabricatio_agent/actions/__init__.py
fabricatio_agent/actions/code.py
fabricatio_agent/capabilities/__init__.py
fabricatio_agent/capabilities/agent.py
fabricatio_agent/cli.py
fabricatio_agent/config.py
fabricatio_agent/models/__init__.py
fabricatio_agent/models/agent.py
fabricatio_agent/py.typed
fabricatio_agent/rust.cp312-win_amd64.pyd
fabricatio_agent/rust.pyi
fabricatio_agent/workflows/__init__.py
fabricatio_agent-0.2.4.dist-info/RECORD
