Metadata-Version: 2.4
Name: fabricatio-agent
Version: 0.2.4
Classifier: License :: OSI Approved :: MIT License
Classifier: Programming Language :: Python :: 3.12
Classifier: Programming Language :: Python :: 3.13
Classifier: Programming Language :: Python :: 3.14
Classifier: Programming Language :: Python :: Implementation :: CPython
Classifier: Typing :: Typed
Requires-Dist: fabricatio-core
Requires-Dist: fabricatio-digest
Requires-Dist: fabricatio-memory
Requires-Dist: fabricatio-improve
Requires-Dist: fabricatio-rule
Requires-Dist: fabricatio-judge
Requires-Dist: fabricatio-capabilities
Requires-Dist: fabricatio-diff
Requires-Dist: fabricatio-thinking
Requires-Dist: fabricatio-question
Requires-Dist: fabricatio-tool
Requires-Dist: fabricatio-team
Requires-Dist: fabricatio-capable
Requires-Dist: fabricatio-checkpoint
Requires-Dist: typer-slim[standard]>=0.15.2 ; extra == 'cli'
Requires-Dist: fabricatio-actions ; extra == 'cli'
Requires-Dist: fabricatio-agent[cli] ; extra == 'cli-plot'
Requires-Dist: fabricatio-plot ; extra == 'cli-plot'
Requires-Dist: fabricatio-agent[cli] ; extra == 'cli-full'
Requires-Dist: fabricatio-agent[cli-plot] ; extra == 'cli-full'
Provides-Extra: cli
Provides-Extra: cli-plot
Provides-Extra: cli-full
Summary: An extension of fabricatio
Author-email: Whth <zettainspector@foxmail.com>
License-Expression: MIT
Requires-Python: >=3.12, <3.15
Project-URL: Homepage, https://github.com/Whth/fabricatio
Project-URL: Repository, https://github.com/Whth/fabricatio
Project-URL: Issues, https://github.com/Whth/fabricatio/issues
